EventHandler_Edog0049a/EventHandler.py
EventHandler_Edog0049a/__init__.py
eventhandler_edog0049a-0.2.0.dist-info/METADATA
eventhandler_edog0049a-0.2.0.dist-info/WHEEL
eventhandler_edog0049a-0.2.0.dist-info/licenses/LICENSE.txt
eventhandler_edog0049a-0.2.0.dist-info/RECORD
